{"openapi":"3.1.0","info":{"title":"Edo LMS","version":"0.1.0"},"paths":{"/api/v1/auth/login":{"post":{"tags":["Authentication"],"summary":"Login For Access Token","operationId":"login_for_access_token_api_v1_auth_login_post","requestBody":{"content":{"application/x-www-form-urlencoded":{"schema":{"$ref":"#/components/schemas/Body_login_for_access_token_api_v1_auth_login_post"}}},"required":true},"responses":{"200":{"description":"Successful Response","content":{"application/json":{"schema":{"$ref":"#/components/schemas/Token"}}}},"422":{"description":"Validation Error","content":{"application/json":{"schema":{"$ref":"#/components/schemas/HTTPValidationError"}}}}}}},"/api/v1/auth/refresh":{"post":{"tags":["Authentication"],"summary":"Refresh Access Token","description":"Refresh an access token using a refresh token.","operationId":"refresh_access_token_api_v1_auth_refresh_post","requestBody":{"content":{"application/json":{"schema":{"$ref":"#/components/schemas/RefreshTokenRequest"}}},"required":true},"responses":{"200":{"description":"Successful Response","content":{"application/json":{"schema":{"$ref":"#/components/schemas/AccessTokenResponse"}}}},"422":{"description":"Validation Error","content":{"application/json":{"schema":{"$ref":"#/components/schemas/HTTPValidationError"}}}}}}},"/api/v1/auth/logout":{"post":{"tags":["Authentication"],"summary":"Logout","description":"Logout user by invalidating their refresh token.","operationId":"logout_api_v1_auth_logout_post","responses":{"200":{"description":"Successful Response","content":{"application/json":{"schema":{}}}}},"security":[{"OAuth2PasswordBearer":[]}]}},"/api/v1/auth/logout-all":{"post":{"tags":["Authentication"],"summary":"Logout All Devices","description":"Logout user from all devices by clearing all refresh tokens.","operationId":"logout_all_devices_api_v1_auth_logout_all_post","responses":{"200":{"description":"Successful Response","content":{"application/json":{"schema":{}}}}},"security":[{"OAuth2PasswordBearer":[]}]}},"/api/v1/users/":{"get":{"tags":["Users"],"summary":"Get Users","operationId":"get_users_api_v1_users__get","responses":{"200":{"description":"Successful Response","content":{"application/json":{"schema":{"items":{"$ref":"#/components/schemas/User"},"type":"array","title":"Response Get Users Api V1 Users  Get"}}}}},"security":[{"OAuth2PasswordBearer":[]}]},"post":{"tags":["Users"],"summary":"Create User","operationId":"create_user_api_v1_users__post","requestBody":{"content":{"application/json":{"schema":{"$ref":"#/components/schemas/UserCreate"}}},"required":true},"responses":{"200":{"description":"Successful Response","content":{"application/json":{"schema":{"$ref":"#/components/schemas/User"}}}},"422":{"description":"Validation Error","content":{"application/json":{"schema":{"$ref":"#/components/schemas/HTTPValidationError"}}}}},"security":[{"OAuth2PasswordBearer":[]}]}},"/api/v1/users/by-role/{role}":{"get":{"tags":["Users"],"summary":"Get Users By Role","operationId":"get_users_by_role_api_v1_users_by_role__role__get","security":[{"OAuth2PasswordBearer":[]}],"parameters":[{"name":"role","in":"path","required":true,"schema":{"type":"string","title":"Role"}}],"responses":{"200":{"description":"Successful Response","content":{"application/json":{"schema":{"type":"array","items":{"$ref":"#/components/schemas/User"},"title":"Response Get Users By Role Api V1 Users By Role  Role  Get"}}}},"422":{"description":"Validation Error","content":{"application/json":{"schema":{"$ref":"#/components/schemas/HTTPValidationError"}}}}}}},"/api/v1/users/me":{"get":{"tags":["Users"],"summary":"Get Me","operationId":"get_me_api_v1_users_me_get","responses":{"200":{"description":"Successful Response","content":{"application/json":{"schema":{}}}}},"security":[{"OAuth2PasswordBearer":[]}]}},"/api/v1/users/{user_id}":{"get":{"tags":["Users"],"summary":"Get User","operationId":"get_user_api_v1_users__user_id__get","security":[{"OAuth2PasswordBearer":[]}],"parameters":[{"name":"user_id","in":"path","required":true,"schema":{"type":"string","format":"uuid","title":"User Id"}}],"responses":{"200":{"description":"Successful Response","content":{"application/json":{"schema":{"$ref":"#/components/schemas/User"}}}},"422":{"description":"Validation Error","content":{"application/json":{"schema":{"$ref":"#/components/schemas/HTTPValidationError"}}}}}},"put":{"tags":["Users"],"summary":"Update User","operationId":"update_user_api_v1_users__user_id__put","security":[{"OAuth2PasswordBearer":[]}],"parameters":[{"name":"user_id","in":"path","required":true,"schema":{"type":"string","format":"uuid","title":"User Id"}}],"requestBody":{"required":true,"content":{"application/json":{"schema":{"$ref":"#/components/schemas/UserUpdate"}}}},"responses":{"200":{"description":"Successful Response","content":{"application/json":{"schema":{"$ref":"#/components/schemas/User"}}}},"422":{"description":"Validation Error","content":{"application/json":{"schema":{"$ref":"#/components/schemas/HTTPValidationError"}}}}}},"delete":{"tags":["Users"],"summary":"Delete User","operationId":"delete_user_api_v1_users__user_id__delete","security":[{"OAuth2PasswordBearer":[]}],"parameters":[{"name":"user_id","in":"path","required":true,"schema":{"type":"string","format":"uuid","title":"User Id"}}],"responses":{"200":{"description":"Successful Response","content":{"application/json":{"schema":{}}}},"422":{"description":"Validation Error","content":{"application/json":{"schema":{"$ref":"#/components/schemas/HTTPValidationError"}}}}}}},"/api/v1/import/upload-csv":{"post":{"tags":["Import"],"summary":"Import Users From Csv","description":"Import users from CSV file upload.","operationId":"import_users_from_csv_api_v1_import_upload_csv_post","requestBody":{"content":{"multipart/form-data":{"schema":{"$ref":"#/components/schemas/Body_import_users_from_csv_api_v1_import_upload_csv_post"}}},"required":true},"responses":{"200":{"description":"Successful Response","content":{"application/json":{"schema":{}}}},"422":{"description":"Validation Error","content":{"application/json":{"schema":{"$ref":"#/components/schemas/HTTPValidationError"}}}}},"security":[{"OAuth2PasswordBearer":[]}]}},"/api/v1/import/upload-excel":{"post":{"tags":["Import"],"summary":"Import Users From Excel","description":"Import users from Excel file upload.","operationId":"import_users_from_excel_api_v1_import_upload_excel_post","requestBody":{"content":{"multipart/form-data":{"schema":{"$ref":"#/components/schemas/Body_import_users_from_excel_api_v1_import_upload_excel_post"}}},"required":true},"responses":{"200":{"description":"Successful Response","content":{"application/json":{"schema":{}}}},"422":{"description":"Validation Error","content":{"application/json":{"schema":{"$ref":"#/components/schemas/HTTPValidationError"}}}}},"security":[{"OAuth2PasswordBearer":[]}]}},"/api/v1/import/from-json":{"post":{"tags":["Import"],"summary":"Import Users From Json","description":"Import users from JSON data.","operationId":"import_users_from_json_api_v1_import_from_json_post","security":[{"OAuth2PasswordBearer":[]}],"parameters":[{"name":"update_existing","in":"query","required":false,"schema":{"type":"boolean","default":false,"title":"Update Existing"}}],"requestBody":{"required":true,"content":{"application/json":{"schema":{"type":"array","items":{"type":"object","additionalProperties":true},"title":"Users Data"}}}},"responses":{"200":{"description":"Successful Response","content":{"application/json":{"schema":{}}}},"422":{"description":"Validation Error","content":{"application/json":{"schema":{"$ref":"#/components/schemas/HTTPValidationError"}}}}}}},"/api/v1/import/template/csv":{"get":{"tags":["Import"],"summary":"Download Csv Template","description":"Download CSV template for user import.","operationId":"download_csv_template_api_v1_import_template_csv_get","responses":{"200":{"description":"Successful Response","content":{"application/json":{"schema":{}}}}}}},"/api/v1/import/template/excel":{"get":{"tags":["Import"],"summary":"Download Excel Template","description":"Download Excel template for user import.","operationId":"download_excel_template_api_v1_import_template_excel_get","responses":{"200":{"description":"Successful Response","content":{"application/json":{"schema":{}}}}}}},"/api/v1/study-programs/":{"post":{"tags":["Study Programs"],"summary":"Create Study Program","description":"Create a new study program. Only accessible to admins and supervisors.\nThe study program supervisor is automatically set to the current user (if supervisor).","operationId":"create_study_program_api_v1_study_programs__post","security":[{"OAuth2PasswordBearer":[]}],"requestBody":{"required":true,"content":{"application/json":{"schema":{"$ref":"#/components/schemas/StudyProgramCreate"}}}},"responses":{"201":{"description":"Successful Response","content":{"application/json":{"schema":{"$ref":"#/components/schemas/StudyProgram"}}}},"422":{"description":"Validation Error","content":{"application/json":{"schema":{"$ref":"#/components/schemas/HTTPValidationError"}}}}}},"get":{"tags":["Study Programs"],"summary":"Read Study Programs","description":"Retrieve a list of study programs based on user role.\n- Admins see all study programs.\n- Supervisors see study programs they supervise.\n- Teachers see study programs they are assigned to.\n- Students see study programs they are enrolled in.","operationId":"read_study_programs_api_v1_study_programs__get","security":[{"OAuth2PasswordBearer":[]}],"parameters":[{"name":"skip","in":"query","required":false,"schema":{"type":"integer","default":0,"title":"Skip"}},{"name":"limit","in":"query","required":false,"schema":{"type":"integer","default":100,"title":"Limit"}}],"responses":{"200":{"description":"Successful Response","content":{"application/json":{"schema":{"type":"array","items":{"$ref":"#/components/schemas/StudyProgram"},"title":"Response Read Study Programs Api V1 Study Programs  Get"}}}},"422":{"description":"Validation Error","content":{"application/json":{"schema":{"$ref":"#/components/schemas/HTTPValidationError"}}}}}}},"/api/v1/study-programs/{study_program_id}":{"get":{"tags":["Study Programs"],"summary":"Read Study Program","description":"Retrieve a single study program by its ID. Accessible based on user permissions.","operationId":"read_study_program_api_v1_study_programs__study_program_id__get","security":[{"OAuth2PasswordBearer":[]}],"parameters":[{"name":"study_program_id","in":"path","required":true,"schema":{"type":"string","format":"uuid","title":"Study Program Id"}}],"responses":{"200":{"description":"Successful Response","content":{"application/json":{"schema":{"$ref":"#/components/schemas/StudyProgram"}}}},"422":{"description":"Validation Error","content":{"application/json":{"schema":{"$ref":"#/components/schemas/HTTPValidationError"}}}}}},"put":{"tags":["Study Programs"],"summary":"Update Study Program","description":"Update a study program.\nOnly accessible to admins or the specific supervisor of the study program.","operationId":"update_study_program_api_v1_study_programs__study_program_id__put","security":[{"OAuth2PasswordBearer":[]}],"parameters":[{"name":"study_program_id","in":"path","required":true,"schema":{"type":"string","format":"uuid","title":"Study Program Id"}}],"requestBody":{"required":true,"content":{"application/json":{"schema":{"$ref":"#/components/schemas/StudyProgramUpdate"}}}},"responses":{"200":{"description":"Successful Response","content":{"application/json":{"schema":{"$ref":"#/components/schemas/StudyProgram"}}}},"422":{"description":"Validation Error","content":{"application/json":{"schema":{"$ref":"#/components/schemas/HTTPValidationError"}}}}}},"delete":{"tags":["Study Programs"],"summary":"Delete Study Program","description":"Delete a study program.\nOnly accessible to admins or the specific supervisor of the study program.","operationId":"delete_study_program_api_v1_study_programs__study_program_id__delete","security":[{"OAuth2PasswordBearer":[]}],"parameters":[{"name":"study_program_id","in":"path","required":true,"schema":{"type":"string","format":"uuid","title":"Study Program Id"}}],"responses":{"204":{"description":"Successful Response"},"422":{"description":"Validation Error","content":{"application/json":{"schema":{"$ref":"#/components/schemas/HTTPValidationError"}}}}}}},"/api/v1/study-programs/{study_program_id}/courses":{"get":{"tags":["Study Programs"],"summary":"Read Study Program Courses","description":"Retrieve all courses for a specific study program.\nAccessible to any user enrolled in the study program, teacher, supervisor, or admin.","operationId":"read_study_program_courses_api_v1_study_programs__study_program_id__courses_get","security":[{"OAuth2PasswordBearer":[]}],"parameters":[{"name":"study_program_id","in":"path","required":true,"schema":{"type":"string","format":"uuid","title":"Study Program Id"}}],"responses":{"200":{"description":"Successful Response","content":{"application/json":{"schema":{"type":"array","items":{"$ref":"#/components/schemas/Course"},"title":"Response Read Study Program Courses Api V1 Study Programs  Study Program Id  Courses Get"}}}},"422":{"description":"Validation Error","content":{"application/json":{"schema":{"$ref":"#/components/schemas/HTTPValidationError"}}}}}}},"/api/v1/study-programs/{study_program_id}/supervisor":{"post":{"tags":["Study Programs"],"summary":"Assign Supervisor To Study Program","description":"Assign a supervisor to a study program. Only admins can do this.","operationId":"assign_supervisor_to_study_program_api_v1_study_programs__study_program_id__supervisor_post","security":[{"OAuth2PasswordBearer":[]}],"parameters":[{"name":"study_program_id","in":"path","required":true,"schema":{"type":"string","format":"uuid","title":"Study Program Id"}}],"requestBody":{"required":true,"content":{"application/json":{"schema":{"$ref":"#/components/schemas/SupervisorAssignment"}}}},"responses":{"200":{"description":"Successful Response","content":{"application/json":{"schema":{"$ref":"#/components/schemas/StudyProgram"}}}},"422":{"description":"Validation Error","content":{"application/json":{"schema":{"$ref":"#/components/schemas/HTTPValidationError"}}}}}}},"/api/v1/study-programs/{study_program_id}/teachers":{"post":{"tags":["Study Programs"],"summary":"Add Teacher To Study Program","description":"Add a teacher to a study program.","operationId":"add_teacher_to_study_program_api_v1_study_programs__study_program_id__teachers_post","security":[{"OAuth2PasswordBearer":[]}],"parameters":[{"name":"study_program_id","in":"path","required":true,"schema":{"type":"string","format":"uuid","title":"Study Program Id"}}],"requestBody":{"required":true,"content":{"application/json":{"schema":{"$ref":"#/components/schemas/StudyProgramUserLink"}}}},"responses":{"200":{"description":"Successful Response","content":{"application/json":{"schema":{"$ref":"#/components/schemas/StudyProgram"}}}},"422":{"description":"Validation Error","content":{"application/json":{"schema":{"$ref":"#/components/schemas/HTTPValidationError"}}}}}}},"/api/v1/study-programs/{study_program_id}/teachers/bulk":{"post":{"tags":["Study Programs"],"summary":"Add Teachers To Study Program","description":"Add multiple teachers to a study program.","operationId":"add_teachers_to_study_program_api_v1_study_programs__study_program_id__teachers_bulk_post","security":[{"OAuth2PasswordBearer":[]}],"parameters":[{"name":"study_program_id","in":"path","required":true,"schema":{"type":"string","format":"uuid","title":"Study Program Id"}}],"requestBody":{"required":true,"content":{"application/json":{"schema":{"$ref":"#/components/schemas/StudyProgramUsersLink"}}}},"responses":{"200":{"description":"Successful Response","content":{"application/json":{"schema":{"$ref":"#/components/schemas/StudyProgram"}}}},"422":{"description":"Validation Error","content":{"application/json":{"schema":{"$ref":"#/components/schemas/HTTPValidationError"}}}}}}},"/api/v1/study-programs/{study_program_id}/teachers/{user_id}":{"delete":{"tags":["Study Programs"],"summary":"Remove Teacher From Study Program","description":"Remove a teacher from a study program.","operationId":"remove_teacher_from_study_program_api_v1_study_programs__study_program_id__teachers__user_id__delete","security":[{"OAuth2PasswordBearer":[]}],"parameters":[{"name":"study_program_id","in":"path","required":true,"schema":{"type":"string","format":"uuid","title":"Study Program Id"}},{"name":"user_id","in":"path","required":true,"schema":{"type":"string","format":"uuid","title":"User Id"}}],"responses":{"200":{"description":"Successful Response","content":{"application/json":{"schema":{"$ref":"#/components/schemas/StudyProgram"}}}},"422":{"description":"Validation Error","content":{"application/json":{"schema":{"$ref":"#/components/schemas/HTTPValidationError"}}}}}}},"/api/v1/study-programs/{study_program_id}/students":{"post":{"tags":["Study Programs"],"summary":"Add Student To Study Program","description":"Add a student to a study program.","operationId":"add_student_to_study_program_api_v1_study_programs__study_program_id__students_post","security":[{"OAuth2PasswordBearer":[]}],"parameters":[{"name":"study_program_id","in":"path","required":true,"schema":{"type":"string","format":"uuid","title":"Study Program Id"}}],"requestBody":{"required":true,"content":{"application/json":{"schema":{"$ref":"#/components/schemas/StudyProgramUserLink"}}}},"responses":{"200":{"description":"Successful Response","content":{"application/json":{"schema":{"$ref":"#/components/schemas/StudyProgram"}}}},"422":{"description":"Validation Error","content":{"application/json":{"schema":{"$ref":"#/components/schemas/HTTPValidationError"}}}}}}},"/api/v1/study-programs/{study_program_id}/students/bulk":{"post":{"tags":["Study Programs"],"summary":"Add Students To Study Program","description":"Add multiple students to a study program.","operationId":"add_students_to_study_program_api_v1_study_programs__study_program_id__students_bulk_post","security":[{"OAuth2PasswordBearer":[]}],"parameters":[{"name":"study_program_id","in":"path","required":true,"schema":{"type":"string","format":"uuid","title":"Study Program Id"}}],"requestBody":{"required":true,"content":{"application/json":{"schema":{"$ref":"#/components/schemas/StudyProgramUsersLink"}}}},"responses":{"200":{"description":"Successful Response","content":{"application/json":{"schema":{"$ref":"#/components/schemas/StudyProgram"}}}},"422":{"description":"Validation Error","content":{"application/json":{"schema":{"$ref":"#/components/schemas/HTTPValidationError"}}}}}}},"/api/v1/study-programs/{study_program_id}/students/{user_id}":{"delete":{"tags":["Study Programs"],"summary":"Remove Student From Study Program","description":"Remove a student from a study program.","operationId":"remove_student_from_study_program_api_v1_study_programs__study_program_id__students__user_id__delete","security":[{"OAuth2PasswordBearer":[]}],"parameters":[{"name":"study_program_id","in":"path","required":true,"schema":{"type":"string","format":"uuid","title":"Study Program Id"}},{"name":"user_id","in":"path","required":true,"schema":{"type":"string","format":"uuid","title":"User Id"}}],"responses":{"200":{"description":"Successful Response","content":{"application/json":{"schema":{"$ref":"#/components/schemas/StudyProgram"}}}},"422":{"description":"Validation Error","content":{"application/json":{"schema":{"$ref":"#/components/schemas/HTTPValidationError"}}}}}}},"/api/v1/courses/":{"get":{"tags":["Courses","Courses"],"summary":"Read Courses","description":"Retrieve courses.\n- If study_program_id is provided, filter courses by study program.\n- If enrolled_to_me is True, return courses the current user is enrolled in.\n- Otherwise, return all courses (admin/supervisor) or courses user is part of.","operationId":"read_courses_api_v1_courses__get","security":[{"OAuth2PasswordBearer":[]}],"parameters":[{"name":"study_program_id","in":"query","required":false,"schema":{"type":"string","format":"uuid","title":"Study Program Id"}},{"name":"enrolled_to_me","in":"query","required":false,"schema":{"type":"boolean","default":false,"title":"Enrolled To Me"}}],"responses":{"200":{"description":"Successful Response","content":{"application/json":{"schema":{"type":"array","items":{"$ref":"#/components/schemas/Course"},"title":"Response Read Courses Api V1 Courses  Get"}}}},"422":{"description":"Validation Error","content":{"application/json":{"schema":{"$ref":"#/components/schemas/HTTPValidationError"}}}}}},"post":{"tags":["Courses","Courses"],"summary":"Create Course","description":"Create a new course.","operationId":"create_course_api_v1_courses__post","security":[{"OAuth2PasswordBearer":[]}],"requestBody":{"required":true,"content":{"application/json":{"schema":{"$ref":"#/components/schemas/CourseCreate"}}}},"responses":{"201":{"description":"Successful Response","content":{"application/json":{"schema":{"$ref":"#/components/schemas/Course"}}}},"422":{"description":"Validation Error","content":{"application/json":{"schema":{"$ref":"#/components/schemas/HTTPValidationError"}}}}}}},"/api/v1/courses/{course_id}":{"get":{"tags":["Courses","Courses"],"summary":"Read Course","description":"Retrieve a single course by its ID.","operationId":"read_course_api_v1_courses__course_id__get","parameters":[{"name":"course_id","in":"path","required":true,"schema":{"type":"string","format":"uuid","title":"Course Id"}}],"responses":{"200":{"description":"Successful Response","content":{"application/json":{"schema":{"$ref":"#/components/schemas/Course"}}}},"422":{"description":"Validation Error","content":{"application/json":{"schema":{"$ref":"#/components/schemas/HTTPValidationError"}}}}}},"put":{"tags":["Courses","Courses"],"summary":"Update Course","description":"Update a course's details.","operationId":"update_course_api_v1_courses__course_id__put","security":[{"OAuth2PasswordBearer":[]}],"parameters":[{"name":"course_id","in":"path","required":true,"schema":{"type":"string","format":"uuid","title":"Course Id"}}],"requestBody":{"required":true,"content":{"application/json":{"schema":{"$ref":"#/components/schemas/CourseUpdate"}}}},"responses":{"200":{"description":"Successful Response","content":{"application/json":{"schema":{"$ref":"#/components/schemas/Course"}}}},"422":{"description":"Validation Error","content":{"application/json":{"schema":{"$ref":"#/components/schemas/HTTPValidationError"}}}}}}},"/api/v1/courses/{course_id}/teachers":{"post":{"tags":["Courses","Courses"],"summary":"Add Teacher To Course","operationId":"add_teacher_to_course_api_v1_courses__course_id__teachers_post","parameters":[{"name":"course_id","in":"path","required":true,"schema":{"type":"string","format":"uuid","title":"Course Id"}},{"name":"teacher_id","in":"query","required":true,"schema":{"type":"string","format":"uuid","title":"Teacher Id"}}],"responses":{"200":{"description":"Successful Response","content":{"application/json":{"schema":{"$ref":"#/components/schemas/User"}}}},"422":{"description":"Validation Error","content":{"application/json":{"schema":{"$ref":"#/components/schemas/HTTPValidationError"}}}}}}},"/api/v1/courses/{course_id}/teachers/{teacher_id}":{"delete":{"tags":["Courses","Courses"],"summary":"Remove Teacher From Course","operationId":"remove_teacher_from_course_api_v1_courses__course_id__teachers__teacher_id__delete","parameters":[{"name":"course_id","in":"path","required":true,"schema":{"type":"string","format":"uuid","title":"Course Id"}},{"name":"teacher_id","in":"path","required":true,"schema":{"type":"string","format":"uuid","title":"Teacher Id"}}],"responses":{"204":{"description":"Successful Response"},"422":{"description":"Validation Error","content":{"application/json":{"schema":{"$ref":"#/components/schemas/HTTPValidationError"}}}}}}},"/api/v1/courses/{course_id}/students":{"post":{"tags":["Courses","Courses"],"summary":"Add Student To Course","operationId":"add_student_to_course_api_v1_courses__course_id__students_post","parameters":[{"name":"course_id","in":"path","required":true,"schema":{"type":"string","format":"uuid","title":"Course Id"}},{"name":"student_id","in":"query","required":true,"schema":{"type":"string","format":"uuid","title":"Student Id"}}],"responses":{"200":{"description":"Successful Response","content":{"application/json":{"schema":{"$ref":"#/components/schemas/User"}}}},"422":{"description":"Validation Error","content":{"application/json":{"schema":{"$ref":"#/components/schemas/HTTPValidationError"}}}}}}},"/api/v1/courses/{course_id}/students/bulk":{"post":{"tags":["Courses","Courses"],"summary":"Add Students To Course Bulk","operationId":"add_students_to_course_bulk_api_v1_courses__course_id__students_bulk_post","parameters":[{"name":"course_id","in":"path","required":true,"schema":{"type":"string","format":"uuid","title":"Course Id"}}],"requestBody":{"required":true,"content":{"application/json":{"schema":{"$ref":"#/components/schemas/CourseUsersLink"}}}},"responses":{"200":{"description":"Successful Response","content":{"application/json":{"schema":{"type":"array","items":{"$ref":"#/components/schemas/User"},"title":"Response Add Students To Course Bulk Api V1 Courses  Course Id  Students Bulk Post"}}}},"422":{"description":"Validation Error","content":{"application/json":{"schema":{"$ref":"#/components/schemas/HTTPValidationError"}}}}}}},"/api/v1/courses/{course_id}/students/{student_id}":{"delete":{"tags":["Courses","Courses"],"summary":"Remove Student From Course","operationId":"remove_student_from_course_api_v1_courses__course_id__students__student_id__delete","parameters":[{"name":"course_id","in":"path","required":true,"schema":{"type":"string","format":"uuid","title":"Course Id"}},{"name":"student_id","in":"path","required":true,"schema":{"type":"string","format":"uuid","title":"Student Id"}}],"responses":{"204":{"description":"Successful Response"},"422":{"description":"Validation Error","content":{"application/json":{"schema":{"$ref":"#/components/schemas/HTTPValidationError"}}}}}}},"/api/v1/courses/{course_id}/news/":{"get":{"tags":["News","News"],"summary":"Read Course News","description":"Retrieve all news for a specific course.","operationId":"read_course_news_api_v1_courses__course_id__news__get","security":[{"OAuth2PasswordBearer":[]}],"parameters":[{"name":"course_id","in":"path","required":true,"schema":{"type":"string","format":"uuid","title":"Course Id"}}],"responses":{"200":{"description":"Successful Response","content":{"application/json":{"schema":{"type":"array","items":{"$ref":"#/components/schemas/News"},"title":"Response Read Course News Api V1 Courses  Course Id  News  Get"}}}},"422":{"description":"Validation Error","content":{"application/json":{"schema":{"$ref":"#/components/schemas/HTTPValidationError"}}}}}},"post":{"tags":["News","News"],"summary":"Create Course News","description":"Create a new news item for a specific course (teacher/admin access).","operationId":"create_course_news_api_v1_courses__course_id__news__post","security":[{"OAuth2PasswordBearer":[]}],"parameters":[{"name":"course_id","in":"path","required":true,"schema":{"type":"string","format":"uuid","title":"Course Id"}}],"requestBody":{"required":true,"content":{"application/json":{"schema":{"$ref":"#/components/schemas/NewsCreate"}}}},"responses":{"201":{"description":"Successful Response","content":{"application/json":{"schema":{"$ref":"#/components/schemas/News"}}}},"422":{"description":"Validation Error","content":{"application/json":{"schema":{"$ref":"#/components/schemas/HTTPValidationError"}}}}}}},"/api/v1/news/{news_id}":{"put":{"tags":["News","News"],"summary":"Update News Item","description":"Update a news item.","operationId":"update_news_item_api_v1_news__news_id__put","security":[{"OAuth2PasswordBearer":[]}],"parameters":[{"name":"news_id","in":"path","required":true,"schema":{"type":"string","format":"uuid","title":"News Id"}}],"requestBody":{"required":true,"content":{"application/json":{"schema":{"$ref":"#/components/schemas/NewsUpdate"}}}},"responses":{"200":{"description":"Successful Response","content":{"application/json":{"schema":{"$ref":"#/components/schemas/News"}}}},"422":{"description":"Validation Error","content":{"application/json":{"schema":{"$ref":"#/components/schemas/HTTPValidationError"}}}}}},"delete":{"tags":["News","News"],"summary":"Delete News Item","description":"Delete a news item.","operationId":"delete_news_item_api_v1_news__news_id__delete","security":[{"OAuth2PasswordBearer":[]}],"parameters":[{"name":"news_id","in":"path","required":true,"schema":{"type":"string","format":"uuid","title":"News Id"}}],"responses":{"204":{"description":"Successful Response"},"422":{"description":"Validation Error","content":{"application/json":{"schema":{"$ref":"#/components/schemas/HTTPValidationError"}}}}}}},"/api/v1/courses/{course_id}/threads":{"get":{"tags":["Forum Threads","Forum"],"summary":"Read Threads For Course","description":"Retrieve all forum threads for a specific course.","operationId":"read_threads_for_course_api_v1_courses__course_id__threads_get","parameters":[{"name":"course_id","in":"path","required":true,"schema":{"type":"string","format":"uuid","title":"Course Id"}}],"responses":{"200":{"description":"Successful Response","content":{"application/json":{"schema":{"type":"array","items":{"$ref":"#/components/schemas/ForumThread"},"title":"Response Read Threads For Course Api V1 Courses  Course Id  Threads Get"}}}},"422":{"description":"Validation Error","content":{"application/json":{"schema":{"$ref":"#/components/schemas/HTTPValidationError"}}}}}},"post":{"tags":["Forum Threads","Forum"],"summary":"Create Thread For Course","description":"Create a new forum thread for a specific course.","operationId":"create_thread_for_course_api_v1_courses__course_id__threads_post","security":[{"OAuth2PasswordBearer":[]}],"parameters":[{"name":"course_id","in":"path","required":true,"schema":{"type":"string","format":"uuid","title":"Course Id"}}],"requestBody":{"required":true,"content":{"application/json":{"schema":{"$ref":"#/components/schemas/ForumThreadCreate"}}}},"responses":{"200":{"description":"Successful Response","content":{"application/json":{"schema":{"$ref":"#/components/schemas/ForumThread"}}}},"422":{"description":"Validation Error","content":{"application/json":{"schema":{"$ref":"#/components/schemas/HTTPValidationError"}}}}}}},"/api/v1/forum-threads/{thread_id}":{"get":{"tags":["Forum Threads","Forum"],"summary":"Read Thread","description":"Retrieve a single forum thread with all its posts.","operationId":"read_thread_api_v1_forum_threads__thread_id__get","parameters":[{"name":"thread_id","in":"path","required":true,"schema":{"type":"string","format":"uuid","title":"Thread Id"}}],"responses":{"200":{"description":"Successful Response","content":{"application/json":{"schema":{"$ref":"#/components/schemas/ForumThreadWithPosts"}}}},"422":{"description":"Validation Error","content":{"application/json":{"schema":{"$ref":"#/components/schemas/HTTPValidationError"}}}}}},"delete":{"tags":["Forum Threads","Forum"],"summary":"Delete Forum Thread","description":"Delete a forum thread.","operationId":"delete_forum_thread_api_v1_forum_threads__thread_id__delete","security":[{"OAuth2PasswordBearer":[]}],"parameters":[{"name":"thread_id","in":"path","required":true,"schema":{"type":"string","format":"uuid","title":"Thread Id"}}],"responses":{"204":{"description":"Successful Response"},"422":{"description":"Validation Error","content":{"application/json":{"schema":{"$ref":"#/components/schemas/HTTPValidationError"}}}}}}},"/api/v1/forum-threads/{thread_id}/posts":{"post":{"tags":["Forum Posts","Forum"],"summary":"Create Post In Thread","description":"Create a new post in a specific forum thread.","operationId":"create_post_in_thread_api_v1_forum_threads__thread_id__posts_post","security":[{"OAuth2PasswordBearer":[]}],"parameters":[{"name":"thread_id","in":"path","required":true,"schema":{"type":"string","format":"uuid","title":"Thread Id"}}],"requestBody":{"required":true,"content":{"application/json":{"schema":{"$ref":"#/components/schemas/ForumPostCreate"}}}},"responses":{"201":{"description":"Successful Response","content":{"application/json":{"schema":{"$ref":"#/components/schemas/ForumPost"}}}},"422":{"description":"Validation Error","content":{"application/json":{"schema":{"$ref":"#/components/schemas/HTTPValidationError"}}}}}}},"/api/v1/forum-posts/{post_id}":{"put":{"tags":["Forum Posts","Forum"],"summary":"Update Post","description":"Update a forum post.","operationId":"update_post_api_v1_forum_posts__post_id__put","security":[{"OAuth2PasswordBearer":[]}],"parameters":[{"name":"post_id","in":"path","required":true,"schema":{"type":"string","format":"uuid","title":"Post Id"}}],"requestBody":{"required":true,"content":{"application/json":{"schema":{"$ref":"#/components/schemas/ForumPostCreate"}}}},"responses":{"200":{"description":"Successful Response","content":{"application/json":{"schema":{"$ref":"#/components/schemas/ForumPost"}}}},"422":{"description":"Validation Error","content":{"application/json":{"schema":{"$ref":"#/components/schemas/HTTPValidationError"}}}}}},"delete":{"tags":["Forum Posts","Forum"],"summary":"Delete Post","description":"Delete a forum post.","operationId":"delete_post_api_v1_forum_posts__post_id__delete","security":[{"OAuth2PasswordBearer":[]}],"parameters":[{"name":"post_id","in":"path","required":true,"schema":{"type":"string","format":"uuid","title":"Post Id"}}],"responses":{"204":{"description":"Successful Response"},"422":{"description":"Validation Error","content":{"application/json":{"schema":{"$ref":"#/components/schemas/HTTPValidationError"}}}}}}},"/api/v1/courses/{course_id}/assignments":{"get":{"tags":["Assignments","Assignments"],"summary":"Read Assignments For Course","description":"Retrieve all assignments for a specific course.","operationId":"read_assignments_for_course_api_v1_courses__course_id__assignments_get","security":[{"OAuth2PasswordBearer":[]}],"parameters":[{"name":"course_id","in":"path","required":true,"schema":{"type":"string","format":"uuid","title":"Course Id"}}],"responses":{"200":{"description":"Successful Response","content":{"application/json":{"schema":{"type":"array","items":{"$ref":"#/components/schemas/Assignment"},"title":"Response Read Assignments For Course Api V1 Courses  Course Id  Assignments Get"}}}},"422":{"description":"Validation Error","content":{"application/json":{"schema":{"$ref":"#/components/schemas/HTTPValidationError"}}}}}},"post":{"tags":["Assignments","Assignments"],"summary":"Create Assignment For Course","description":"Create a new assignment for a specific course (Teachers/Admins only).","operationId":"create_assignment_for_course_api_v1_courses__course_id__assignments_post","security":[{"OAuth2PasswordBearer":[]}],"parameters":[{"name":"course_id","in":"path","required":true,"schema":{"type":"string","format":"uuid","title":"Course Id"}}],"requestBody":{"required":true,"content":{"application/json":{"schema":{"$ref":"#/components/schemas/AssignmentCreate"}}}},"responses":{"201":{"description":"Successful Response","content":{"application/json":{"schema":{"$ref":"#/components/schemas/Assignment"}}}},"422":{"description":"Validation Error","content":{"application/json":{"schema":{"$ref":"#/components/schemas/HTTPValidationError"}}}}}}},"/api/v1/assignments/{assignment_id}":{"delete":{"tags":["Assignments","Assignments"],"summary":"Delete Assignment","description":"Delete an assignment (Teachers/Admins only).","operationId":"delete_assignment_api_v1_assignments__assignment_id__delete","security":[{"OAuth2PasswordBearer":[]}],"parameters":[{"name":"assignment_id","in":"path","required":true,"schema":{"type":"string","format":"uuid","title":"Assignment Id"}}],"responses":{"204":{"description":"Successful Response"},"422":{"description":"Validation Error","content":{"application/json":{"schema":{"$ref":"#/components/schemas/HTTPValidationError"}}}}}},"get":{"tags":["Assignments","Assignments"],"summary":"Read Assignment With Submissions","description":"Retrieve a single assignment with all its submissions (Teachers/Admins only).","operationId":"read_assignment_with_submissions_api_v1_assignments__assignment_id__get","security":[{"OAuth2PasswordBearer":[]}],"parameters":[{"name":"assignment_id","in":"path","required":true,"schema":{"type":"string","format":"uuid","title":"Assignment Id"}}],"responses":{"200":{"description":"Successful Response","content":{"application/json":{"schema":{"$ref":"#/components/schemas/AssignmentWithSubmissions"}}}},"422":{"description":"Validation Error","content":{"application/json":{"schema":{"$ref":"#/components/schemas/HTTPValidationError"}}}}}}},"/api/v1/assignments/{assignment_id}/student-view":{"get":{"tags":["Assignments","Assignments"],"summary":"Read Assignment For Student","description":"Retrieve a single assignment's details (for students).","operationId":"read_assignment_for_student_api_v1_assignments__assignment_id__student_view_get","security":[{"OAuth2PasswordBearer":[]}],"parameters":[{"name":"assignment_id","in":"path","required":true,"schema":{"type":"string","format":"uuid","title":"Assignment Id"}}],"responses":{"200":{"description":"Successful Response","content":{"application/json":{"schema":{"$ref":"#/components/schemas/Assignment"}}}},"422":{"description":"Validation Error","content":{"application/json":{"schema":{"$ref":"#/components/schemas/HTTPValidationError"}}}}}}},"/api/v1/assignments/{assignment_id}/my-submission":{"get":{"tags":["Assignments","Assignments"],"summary":"Read My Submission","description":"Retrieve the current user's submission for an assignment.","operationId":"read_my_submission_api_v1_assignments__assignment_id__my_submission_get","security":[{"OAuth2PasswordBearer":[]}],"parameters":[{"name":"assignment_id","in":"path","required":true,"schema":{"type":"string","format":"uuid","title":"Assignment Id"}}],"responses":{"200":{"description":"Successful Response","content":{"application/json":{"schema":{"anyOf":[{"$ref":"#/components/schemas/Submission"},{"type":"null"}],"title":"Response Read My Submission Api V1 Assignments  Assignment Id  My Submission Get"}}}},"422":{"description":"Validation Error","content":{"application/json":{"schema":{"$ref":"#/components/schemas/HTTPValidationError"}}}}}}},"/api/v1/assignments/{assignment_id}/submissions":{"post":{"tags":["Assignments","Assignments"],"summary":"Create Or Update Submission","description":"Create or update a submission for an assignment (Students only).","operationId":"create_or_update_submission_api_v1_assignments__assignment_id__submissions_post","security":[{"OAuth2PasswordBearer":[]}],"parameters":[{"name":"assignment_id","in":"path","required":true,"schema":{"type":"string","format":"uuid","title":"Assignment Id"}}],"requestBody":{"required":true,"content":{"application/json":{"schema":{"$ref":"#/components/schemas/SubmissionCreate"}}}},"responses":{"200":{"description":"Successful Response","content":{"application/json":{"schema":{"$ref":"#/components/schemas/Submission"}}}},"422":{"description":"Validation Error","content":{"application/json":{"schema":{"$ref":"#/components/schemas/HTTPValidationError"}}}}}},"delete":{"tags":["Assignments","Assignments"],"summary":"Delete My Submission","description":"Delete the current user's submission for an assignment (Students only).","operationId":"delete_my_submission_api_v1_assignments__assignment_id__submissions_delete","security":[{"OAuth2PasswordBearer":[]}],"parameters":[{"name":"assignment_id","in":"path","required":true,"schema":{"type":"string","format":"uuid","title":"Assignment Id"}}],"responses":{"204":{"description":"Successful Response"},"422":{"description":"Validation Error","content":{"application/json":{"schema":{"$ref":"#/components/schemas/HTTPValidationError"}}}}}}},"/api/v1/assignments/{assignment_id}/submissions/with-files":{"post":{"tags":["Assignments","Assignments"],"summary":"Create Or Update Submission With Files","description":"Create or update a submission with files for an assignment (Students only).","operationId":"create_or_update_submission_with_files_api_v1_assignments__assignment_id__submissions_with_files_post","security":[{"OAuth2PasswordBearer":[]}],"parameters":[{"name":"assignment_id","in":"path","required":true,"schema":{"type":"string","format":"uuid","title":"Assignment Id"}}],"requestBody":{"content":{"multipart/form-data":{"schema":{"$ref":"#/components/schemas/Body_create_or_update_submission_with_files_api_v1_assignments__assignment_id__submissions_with_files_post"}}}},"responses":{"200":{"description":"Successful Response","content":{"application/json":{"schema":{"$ref":"#/components/schemas/Submission"}}}},"422":{"description":"Validation Error","content":{"application/json":{"schema":{"$ref":"#/components/schemas/HTTPValidationError"}}}}}}},"/api/v1/files/{file_type}/{filename}":{"get":{"tags":["Assignments"],"summary":"Download File","description":"Download a file by filename and type.","operationId":"download_file_api_v1_files__file_type___filename__get","parameters":[{"name":"file_type","in":"path","required":true,"schema":{"type":"string","title":"File Type"}},{"name":"filename","in":"path","required":true,"schema":{"type":"string","title":"Filename"}}],"responses":{"200":{"description":"Successful Response","content":{"application/json":{"schema":{}}}},"422":{"description":"Validation Error","content":{"application/json":{"schema":{"$ref":"#/components/schemas/HTTPValidationError"}}}}}}},"/api/v1/lectures/":{"get":{"tags":["Lectures"],"summary":"Read Lectures By Course","description":"Gets all lectures for a specific course.","operationId":"read_lectures_by_course_api_v1_lectures__get","security":[{"OAuth2PasswordBearer":[]}],"parameters":[{"name":"course_id","in":"query","required":true,"schema":{"type":"string","format":"uuid","title":"Course Id"}}],"responses":{"200":{"description":"Successful Response","content":{"application/json":{"schema":{"type":"array","items":{"$ref":"#/components/schemas/Lecture"},"title":"Response Read Lectures By Course Api V1 Lectures  Get"}}}},"422":{"description":"Validation Error","content":{"application/json":{"schema":{"$ref":"#/components/schemas/HTTPValidationError"}}}}}},"post":{"tags":["Lectures"],"summary":"Create Lecture","operationId":"create_lecture_api_v1_lectures__post","security":[{"OAuth2PasswordBearer":[]}],"requestBody":{"required":true,"content":{"application/json":{"schema":{"$ref":"#/components/schemas/LectureCreate"}}}},"responses":{"201":{"description":"Successful Response","content":{"application/json":{"schema":{"$ref":"#/components/schemas/Lecture"}}}},"422":{"description":"Validation Error","content":{"application/json":{"schema":{"$ref":"#/components/schemas/HTTPValidationError"}}}}}}},"/api/v1/lectures/{lecture_id}":{"get":{"tags":["Lectures"],"summary":"Read Lecture","operationId":"read_lecture_api_v1_lectures__lecture_id__get","security":[{"OAuth2PasswordBearer":[]}],"parameters":[{"name":"lecture_id","in":"path","required":true,"schema":{"type":"string","format":"uuid","title":"Lecture Id"}}],"responses":{"200":{"description":"Successful Response","content":{"application/json":{"schema":{"$ref":"#/components/schemas/Lecture"}}}},"422":{"description":"Validation Error","content":{"application/json":{"schema":{"$ref":"#/components/schemas/HTTPValidationError"}}}}}},"put":{"tags":["Lectures"],"summary":"Update Lecture","operationId":"update_lecture_api_v1_lectures__lecture_id__put","security":[{"OAuth2PasswordBearer":[]}],"parameters":[{"name":"lecture_id","in":"path","required":true,"schema":{"type":"string","format":"uuid","title":"Lecture Id"}}],"requestBody":{"required":true,"content":{"application/json":{"schema":{"$ref":"#/components/schemas/LectureUpdate"}}}},"responses":{"200":{"description":"Successful Response","content":{"application/json":{"schema":{"$ref":"#/components/schemas/Lecture"}}}},"422":{"description":"Validation Error","content":{"application/json":{"schema":{"$ref":"#/components/schemas/HTTPValidationError"}}}}}},"delete":{"tags":["Lectures"],"summary":"Delete Lecture","operationId":"delete_lecture_api_v1_lectures__lecture_id__delete","security":[{"OAuth2PasswordBearer":[]}],"parameters":[{"name":"lecture_id","in":"path","required":true,"schema":{"type":"string","format":"uuid","title":"Lecture Id"}}],"responses":{"204":{"description":"Successful Response"},"422":{"description":"Validation Error","content":{"application/json":{"schema":{"$ref":"#/components/schemas/HTTPValidationError"}}}}}}},"/api/v1/lectures/upload-files/{lecture_id}":{"post":{"tags":["Lectures"],"summary":"Upload Lecture Files","description":"Upload files for a specific lecture.","operationId":"upload_lecture_files_api_v1_lectures_upload_files__lecture_id__post","security":[{"OAuth2PasswordBearer":[]}],"parameters":[{"name":"lecture_id","in":"path","required":true,"schema":{"type":"string","format":"uuid","title":"Lecture Id"}}],"requestBody":{"required":true,"content":{"multipart/form-data":{"schema":{"$ref":"#/components/schemas/Body_upload_lecture_files_api_v1_lectures_upload_files__lecture_id__post"}}}},"responses":{"200":{"description":"Successful Response","content":{"application/json":{"schema":{}}}},"422":{"description":"Validation Error","content":{"application/json":{"schema":{"$ref":"#/components/schemas/HTTPValidationError"}}}}}}},"/api/v1/lectures/download/{lecture_id}/{filename}":{"get":{"tags":["Lectures"],"summary":"Download Lecture File","description":"Download a specific file from a lecture.","operationId":"download_lecture_file_api_v1_lectures_download__lecture_id___filename__get","security":[{"OAuth2PasswordBearer":[]}],"parameters":[{"name":"lecture_id","in":"path","required":true,"schema":{"type":"string","format":"uuid","title":"Lecture Id"}},{"name":"filename","in":"path","required":true,"schema":{"type":"string","title":"Filename"}}],"responses":{"200":{"description":"Successful Response","content":{"application/json":{"schema":{}}}},"422":{"description":"Validation Error","content":{"application/json":{"schema":{"$ref":"#/components/schemas/HTTPValidationError"}}}}}}},"/api/v1/lecture-files/{lecture_id}/files":{"get":{"tags":["Lecture Files"],"summary":"Get Lecture Files","description":"Gets all files for a specific lecture, optionally filtered by folder.","operationId":"get_lecture_files_api_v1_lecture_files__lecture_id__files_get","security":[{"OAuth2PasswordBearer":[]}],"parameters":[{"name":"lecture_id","in":"path","required":true,"schema":{"type":"string","format":"uuid","title":"Lecture Id"}},{"name":"folder_name","in":"query","required":false,"schema":{"anyOf":[{"type":"string"},{"type":"null"}],"title":"Folder Name"}}],"responses":{"200":{"description":"Successful Response","content":{"application/json":{"schema":{"type":"array","items":{"$ref":"#/components/schemas/LectureFile"},"title":"Response Get Lecture Files Api V1 Lecture Files  Lecture Id  Files Get"}}}},"422":{"description":"Validation Error","content":{"application/json":{"schema":{"$ref":"#/components/schemas/HTTPValidationError"}}}}}}},"/api/v1/lecture-files/{lecture_id}/folders":{"get":{"tags":["Lecture Files"],"summary":"Get Lecture Folders","description":"Gets all folders for a specific lecture.","operationId":"get_lecture_folders_api_v1_lecture_files__lecture_id__folders_get","security":[{"OAuth2PasswordBearer":[]}],"parameters":[{"name":"lecture_id","in":"path","required":true,"schema":{"type":"string","format":"uuid","title":"Lecture Id"}}],"responses":{"200":{"description":"Successful Response","content":{"application/json":{"schema":{"type":"array","items":{"$ref":"#/components/schemas/LectureFile"},"title":"Response Get Lecture Folders Api V1 Lecture Files  Lecture Id  Folders Get"}}}},"422":{"description":"Validation Error","content":{"application/json":{"schema":{"$ref":"#/components/schemas/HTTPValidationError"}}}}}},"post":{"tags":["Lecture Files"],"summary":"Create Lecture Folder","description":"Creates a new folder for a lecture.","operationId":"create_lecture_folder_api_v1_lecture_files__lecture_id__folders_post","security":[{"OAuth2PasswordBearer":[]}],"parameters":[{"name":"lecture_id","in":"path","required":true,"schema":{"type":"string","format":"uuid","title":"Lecture Id"}}],"requestBody":{"required":true,"content":{"application/json":{"schema":{"type":"object","additionalProperties":true,"title":"Folder Data"}}}},"responses":{"200":{"description":"Successful Response","content":{"application/json":{"schema":{"$ref":"#/components/schemas/LectureFile"}}}},"422":{"description":"Validation Error","content":{"application/json":{"schema":{"$ref":"#/components/schemas/HTTPValidationError"}}}}}}},"/api/v1/lecture-files/{lecture_id}/upload":{"post":{"tags":["Lecture Files"],"summary":"Upload Lecture Files","description":"Upload files for a specific lecture.","operationId":"upload_lecture_files_api_v1_lecture_files__lecture_id__upload_post","security":[{"OAuth2PasswordBearer":[]}],"parameters":[{"name":"lecture_id","in":"path","required":true,"schema":{"type":"string","format":"uuid","title":"Lecture Id"}},{"name":"folder_name","in":"query","required":false,"schema":{"anyOf":[{"type":"string"},{"type":"null"}],"title":"Folder Name"}}],"requestBody":{"required":true,"content":{"multipart/form-data":{"schema":{"$ref":"#/components/schemas/Body_upload_lecture_files_api_v1_lecture_files__lecture_id__upload_post"}}}},"responses":{"200":{"description":"Successful Response","content":{"application/json":{"schema":{}}}},"422":{"description":"Validation Error","content":{"application/json":{"schema":{"$ref":"#/components/schemas/HTTPValidationError"}}}}}}},"/api/v1/lecture-files/download/{file_id}":{"get":{"tags":["Lecture Files"],"summary":"Download Lecture File","description":"Download a specific file.","operationId":"download_lecture_file_api_v1_lecture_files_download__file_id__get","security":[{"OAuth2PasswordBearer":[]}],"parameters":[{"name":"file_id","in":"path","required":true,"schema":{"type":"string","format":"uuid","title":"File Id"}}],"responses":{"200":{"description":"Successful Response","content":{"application/json":{"schema":{}}}},"422":{"description":"Validation Error","content":{"application/json":{"schema":{"$ref":"#/components/schemas/HTTPValidationError"}}}}}}},"/api/v1/lecture-files/{file_id}":{"delete":{"tags":["Lecture Files"],"summary":"Delete Lecture File","description":"Delete a specific file or folder.","operationId":"delete_lecture_file_api_v1_lecture_files__file_id__delete","security":[{"OAuth2PasswordBearer":[]}],"parameters":[{"name":"file_id","in":"path","required":true,"schema":{"type":"string","format":"uuid","title":"File Id"}}],"responses":{"204":{"description":"Successful Response"},"422":{"description":"Validation Error","content":{"application/json":{"schema":{"$ref":"#/components/schemas/HTTPValidationError"}}}}}}},"/api/v1/calendar/my-events":{"get":{"tags":["Calendar","Calendar"],"summary":"Get My Events","description":"Get calendar events for the current user.\n- Returns academic events (holidays, breaks, etc.) for all users\n- For students: also returns assignments and course schedule events from their enrolled courses","operationId":"get_my_events_api_v1_calendar_my_events_get","responses":{"200":{"description":"Successful Response","content":{"application/json":{"schema":{}}}}},"security":[{"OAuth2PasswordBearer":[]}]}},"/api/v1/admin/stats":{"get":{"tags":["Admin"],"summary":"Get Admin Stats","description":"Get key statistics for the admin dashboard.","operationId":"get_admin_stats_api_v1_admin_stats_get","responses":{"200":{"description":"Successful Response","content":{"application/json":{"schema":{"$ref":"#/components/schemas/AdminStats"}}}}},"security":[{"OAuth2PasswordBearer":[]}]}},"/api/v1/admin/calendar/events":{"get":{"tags":["Admin"],"summary":"Get Calendar Events","description":"Get calendar events for admin dashboard.","operationId":"get_calendar_events_api_v1_admin_calendar_events_get","security":[{"OAuth2PasswordBearer":[]}],"parameters":[{"name":"course_id","in":"query","required":false,"schema":{"anyOf":[{"type":"string"},{"type":"null"}],"title":"Course Id"}},{"name":"study_program_id","in":"query","required":false,"schema":{"anyOf":[{"type":"string"},{"type":"null"}],"title":"Study Program Id"}}],"responses":{"200":{"description":"Successful Response","content":{"application/json":{"schema":{"type":"array","items":{"type":"object","additionalProperties":true},"title":"Response Get Calendar Events Api V1 Admin Calendar Events Get"}}}},"422":{"description":"Validation Error","content":{"application/json":{"schema":{"$ref":"#/components/schemas/HTTPValidationError"}}}}}}},"/api/v1/admin/academic-events":{"get":{"tags":["Admin"],"summary":"Get Academic Events","description":"Get all academic events.","operationId":"get_academic_events_api_v1_admin_academic_events_get","responses":{"200":{"description":"Successful Response","content":{"application/json":{"schema":{"items":{"$ref":"#/components/schemas/AcademicEventResponse"},"type":"array","title":"Response Get Academic Events Api V1 Admin Academic Events Get"}}}}},"security":[{"OAuth2PasswordBearer":[]}]},"post":{"tags":["Admin"],"summary":"Create Academic Event","description":"Create a new academic event.","operationId":"create_academic_event_api_v1_admin_academic_events_post","requestBody":{"content":{"application/json":{"schema":{"$ref":"#/components/schemas/AcademicEventCreate"}}},"required":true},"responses":{"200":{"description":"Successful Response","content":{"application/json":{"schema":{"$ref":"#/components/schemas/AcademicEventResponse"}}}},"422":{"description":"Validation Error","content":{"application/json":{"schema":{"$ref":"#/components/schemas/HTTPValidationError"}}}}},"security":[{"OAuth2PasswordBearer":[]}]}},"/api/v1/admin/academic-events/{event_id}":{"get":{"tags":["Admin"],"summary":"Get Academic Event","description":"Get a specific academic event by ID.","operationId":"get_academic_event_api_v1_admin_academic_events__event_id__get","security":[{"OAuth2PasswordBearer":[]}],"parameters":[{"name":"event_id","in":"path","required":true,"schema":{"type":"string","title":"Event Id"}}],"responses":{"200":{"description":"Successful Response","content":{"application/json":{"schema":{"$ref":"#/components/schemas/AcademicEventResponse"}}}},"422":{"description":"Validation Error","content":{"application/json":{"schema":{"$ref":"#/components/schemas/HTTPValidationError"}}}}}},"put":{"tags":["Admin"],"summary":"Update Academic Event","description":"Update an academic event.","operationId":"update_academic_event_api_v1_admin_academic_events__event_id__put","security":[{"OAuth2PasswordBearer":[]}],"parameters":[{"name":"event_id","in":"path","required":true,"schema":{"type":"string","title":"Event Id"}}],"requestBody":{"required":true,"content":{"application/json":{"schema":{"$ref":"#/components/schemas/AcademicEventUpdate"}}}},"responses":{"200":{"description":"Successful Response","content":{"application/json":{"schema":{"$ref":"#/components/schemas/AcademicEventResponse"}}}},"422":{"description":"Validation Error","content":{"application/json":{"schema":{"$ref":"#/components/schemas/HTTPValidationError"}}}}}},"delete":{"tags":["Admin"],"summary":"Delete Academic Event","description":"Delete an academic event.","operationId":"delete_academic_event_api_v1_admin_academic_events__event_id__delete","security":[{"OAuth2PasswordBearer":[]}],"parameters":[{"name":"event_id","in":"path","required":true,"schema":{"type":"string","title":"Event Id"}}],"responses":{"200":{"description":"Successful Response","content":{"application/json":{"schema":{}}}},"422":{"description":"Validation Error","content":{"application/json":{"schema":{"$ref":"#/components/schemas/HTTPValidationError"}}}}}}},"/api/v1/test-data/create-test-data":{"post":{"tags":["Test Data"],"summary":"Create Test Data","description":"Create comprehensive test data for the system.\nOnly accessible to admin users.","operationId":"create_test_data_api_v1_test_data_create_test_data_post","responses":{"200":{"description":"Successful Response","content":{"application/json":{"schema":{}}}}},"security":[{"OAuth2PasswordBearer":[]}]}},"/":{"get":{"summary":"Read Root","operationId":"read_root__get","responses":{"200":{"description":"Successful Response","content":{"application/json":{"schema":{}}}}}}}},"components":{"schemas":{"AcademicEventCreate":{"properties":{"title":{"type":"string","title":"Title"},"description":{"anyOf":[{"type":"string"},{"type":"null"}],"title":"Description"},"start_date":{"type":"string","format":"date","title":"Start Date"},"end_date":{"anyOf":[{"type":"string","format":"date"},{"type":"null"}],"title":"End Date"},"event_type":{"$ref":"#/components/schemas/EventType"},"color":{"anyOf":[{"type":"string"},{"type":"null"}],"title":"Color","default":"#6c757d"},"academic_year":{"anyOf":[{"type":"string"},{"type":"null"}],"title":"Academic Year"}},"type":"object","required":["title","start_date","event_type"],"title":"AcademicEventCreate"},"AcademicEventResponse":{"properties":{"id":{"type":"string","title":"Id"},"title":{"type":"string","title":"Title"},"description":{"anyOf":[{"type":"string"},{"type":"null"}],"title":"Description"},"start_date":{"type":"string","format":"date","title":"Start Date"},"end_date":{"anyOf":[{"type":"string","format":"date"},{"type":"null"}],"title":"End Date"},"event_type":{"$ref":"#/components/schemas/EventType"},"color":{"type":"string","title":"Color"},"is_active":{"type":"boolean","title":"Is Active"},"academic_year":{"anyOf":[{"type":"string"},{"type":"null"}],"title":"Academic Year"}},"type":"object","required":["id","title","description","start_date","end_date","event_type","color","is_active","academic_year"],"title":"AcademicEventResponse"},"AcademicEventUpdate":{"properties":{"title":{"anyOf":[{"type":"string"},{"type":"null"}],"title":"Title"},"description":{"anyOf":[{"type":"string"},{"type":"null"}],"title":"Description"},"start_date":{"anyOf":[{"type":"string","format":"date"},{"type":"null"}],"title":"Start Date"},"end_date":{"anyOf":[{"type":"string","format":"date"},{"type":"null"}],"title":"End Date"},"event_type":{"anyOf":[{"$ref":"#/components/schemas/EventType"},{"type":"null"}]},"color":{"anyOf":[{"type":"string"},{"type":"null"}],"title":"Color"},"academic_year":{"anyOf":[{"type":"string"},{"type":"null"}],"title":"Academic Year"},"is_active":{"anyOf":[{"type":"boolean"},{"type":"null"}],"title":"Is Active"}},"type":"object","title":"AcademicEventUpdate"},"AccessTokenResponse":{"properties":{"access_token":{"type":"string","title":"Access Token"},"token_type":{"type":"string","title":"Token Type","default":"bearer"},"expires_in":{"type":"integer","title":"Expires In"}},"type":"object","required":["access_token","expires_in"],"title":"AccessTokenResponse"},"AdminStats":{"properties":{"total_users":{"type":"integer","title":"Total Users"},"total_study_programs":{"type":"integer","title":"Total Study Programs"},"total_courses":{"type":"integer","title":"Total Courses"},"active_students":{"type":"integer","title":"Active Students"}},"type":"object","required":["total_users","total_study_programs","total_courses","active_students"],"title":"AdminStats"},"Assignment":{"properties":{"title":{"type":"string","title":"Title"},"description":{"anyOf":[{"type":"string"},{"type":"null"}],"title":"Description"},"due_date":{"anyOf":[{"type":"string","format":"date-time"},{"type":"null"}],"title":"Due Date"},"id":{"type":"string","format":"uuid","title":"Id"},"course_id":{"type":"string","format":"uuid","title":"Course Id"},"created_at":{"type":"string","format":"date-time","title":"Created At"}},"type":"object","required":["title","id","course_id","created_at"],"title":"Assignment"},"AssignmentCreate":{"properties":{"title":{"type":"string","title":"Title"},"description":{"anyOf":[{"type":"string"},{"type":"null"}],"title":"Description"},"due_date":{"anyOf":[{"type":"string","format":"date-time"},{"type":"null"}],"title":"Due Date"}},"type":"object","required":["title"],"title":"AssignmentCreate"},"AssignmentWithSubmissions":{"properties":{"title":{"type":"string","title":"Title"},"description":{"anyOf":[{"type":"string"},{"type":"null"}],"title":"Description"},"due_date":{"anyOf":[{"type":"string","format":"date-time"},{"type":"null"}],"title":"Due Date"},"id":{"type":"string","format":"uuid","title":"Id"},"course_id":{"type":"string","format":"uuid","title":"Course Id"},"created_at":{"type":"string","format":"date-time","title":"Created At"},"submissions":{"items":{"$ref":"#/components/schemas/Submission"},"type":"array","title":"Submissions","default":[]}},"type":"object","required":["title","id","course_id","created_at"],"title":"AssignmentWithSubmissions"},"Body_create_or_update_submission_with_files_api_v1_assignments__assignment_id__submissions_with_files_post":{"properties":{"content":{"anyOf":[{"type":"string"},{"type":"null"}],"title":"Content"},"files":{"items":{"type":"string","format":"binary"},"type":"array","title":"Files","default":[]}},"type":"object","title":"Body_create_or_update_submission_with_files_api_v1_assignments__assignment_id__submissions_with_files_post"},"Body_import_users_from_csv_api_v1_import_upload_csv_post":{"properties":{"file":{"type":"string","format":"binary","title":"File"},"update_existing":{"type":"boolean","title":"Update Existing","default":false},"delimiter":{"type":"string","title":"Delimiter","default":","}},"type":"object","required":["file"],"title":"Body_import_users_from_csv_api_v1_import_upload_csv_post"},"Body_import_users_from_excel_api_v1_import_upload_excel_post":{"properties":{"file":{"type":"string","format":"binary","title":"File"},"update_existing":{"type":"boolean","title":"Update Existing","default":false},"sheet_name":{"type":"string","title":"Sheet Name","default":"0"}},"type":"object","required":["file"],"title":"Body_import_users_from_excel_api_v1_import_upload_excel_post"},"Body_login_for_access_token_api_v1_auth_login_post":{"properties":{"grant_type":{"anyOf":[{"type":"string","pattern":"^password$"},{"type":"null"}],"title":"Grant Type"},"username":{"type":"string","title":"Username"},"password":{"type":"string","format":"password","title":"Password"},"scope":{"type":"string","title":"Scope","default":""},"client_id":{"anyOf":[{"type":"string"},{"type":"null"}],"title":"Client Id"},"client_secret":{"anyOf":[{"type":"string"},{"type":"null"}],"format":"password","title":"Client Secret"}},"type":"object","required":["username","password"],"title":"Body_login_for_access_token_api_v1_auth_login_post"},"Body_upload_lecture_files_api_v1_lecture_files__lecture_id__upload_post":{"properties":{"files":{"items":{"type":"string","format":"binary"},"type":"array","title":"Files"}},"type":"object","required":["files"],"title":"Body_upload_lecture_files_api_v1_lecture_files__lecture_id__upload_post"},"Body_upload_lecture_files_api_v1_lectures_upload_files__lecture_id__post":{"properties":{"files":{"items":{"type":"string","format":"binary"},"type":"array","title":"Files"}},"type":"object","required":["files"],"title":"Body_upload_lecture_files_api_v1_lectures_upload_files__lecture_id__post"},"Course":{"properties":{"title":{"type":"string","title":"Title"},"description":{"anyOf":[{"type":"string"},{"type":"null"}],"title":"Description"},"prerequisites":{"anyOf":[{"type":"string"},{"type":"null"}],"title":"Prerequisites"},"course_topics":{"anyOf":[{"type":"string"},{"type":"null"}],"title":"Course Topics"},"assessment_info":{"anyOf":[{"type":"string"},{"type":"null"}],"title":"Assessment Info"},"reading_materials":{"anyOf":[{"type":"string"},{"type":"null"}],"title":"Reading Materials"},"category":{"anyOf":[{"type":"string"},{"type":"null"}],"title":"Category"},"academic_year":{"anyOf":[{"type":"string"},{"type":"null"}],"title":"Academic Year"},"semester":{"anyOf":[{"type":"string"},{"type":"null"}],"title":"Semester"},"schedule":{"anyOf":[{},{"type":"null"}],"title":"Schedule"},"start_date":{"anyOf":[{"type":"string","format":"date-time"},{"type":"null"}],"title":"Start Date"},"end_date":{"anyOf":[{"type":"string","format":"date-time"},{"type":"null"}],"title":"End Date"},"published":{"anyOf":[{"type":"boolean"},{"type":"null"}],"title":"Published","default":false},"materials":{"anyOf":[{"items":{"type":"string"},"type":"array"},{"type":"null"}],"title":"Materials"},"order":{"anyOf":[{"type":"integer"},{"type":"null"}],"title":"Order","default":1},"id":{"type":"string","format":"uuid","title":"Id"},"study_program_id":{"type":"string","format":"uuid","title":"Study Program Id"},"teachers":{"items":{"$ref":"#/components/schemas/User"},"type":"array","title":"Teachers","default":[]},"students":{"items":{"$ref":"#/components/schemas/User"},"type":"array","title":"Students","default":[]},"study_program":{"anyOf":[{"$ref":"#/components/schemas/StudyProgram"},{"type":"null"}]}},"type":"object","required":["title","id","study_program_id"],"title":"Course"},"CourseCreate":{"properties":{"title":{"type":"string","title":"Title"},"description":{"anyOf":[{"type":"string"},{"type":"null"}],"title":"Description"},"prerequisites":{"anyOf":[{"type":"string"},{"type":"null"}],"title":"Prerequisites"},"course_topics":{"anyOf":[{"type":"string"},{"type":"null"}],"title":"Course Topics"},"assessment_info":{"anyOf":[{"type":"string"},{"type":"null"}],"title":"Assessment Info"},"reading_materials":{"anyOf":[{"type":"string"},{"type":"null"}],"title":"Reading Materials"},"category":{"anyOf":[{"type":"string"},{"type":"null"}],"title":"Category"},"academic_year":{"anyOf":[{"type":"string"},{"type":"null"}],"title":"Academic Year"},"semester":{"anyOf":[{"type":"string"},{"type":"null"}],"title":"Semester"},"schedule":{"anyOf":[{},{"type":"null"}],"title":"Schedule"},"start_date":{"anyOf":[{"type":"string","format":"date-time"},{"type":"null"}],"title":"Start Date"},"end_date":{"anyOf":[{"type":"string","format":"date-time"},{"type":"null"}],"title":"End Date"},"published":{"anyOf":[{"type":"boolean"},{"type":"null"}],"title":"Published","default":false},"materials":{"anyOf":[{"items":{"type":"string"},"type":"array"},{"type":"null"}],"title":"Materials"},"order":{"anyOf":[{"type":"integer"},{"type":"null"}],"title":"Order","default":1},"study_program_id":{"type":"string","format":"uuid","title":"Study Program Id"}},"type":"object","required":["title","study_program_id"],"title":"CourseCreate"},"CourseUpdate":{"properties":{"title":{"anyOf":[{"type":"string"},{"type":"null"}],"title":"Title"},"description":{"anyOf":[{"type":"string"},{"type":"null"}],"title":"Description"},"prerequisites":{"anyOf":[{"type":"string"},{"type":"null"}],"title":"Prerequisites"},"course_topics":{"anyOf":[{"type":"string"},{"type":"null"}],"title":"Course Topics"},"assessment_info":{"anyOf":[{"type":"string"},{"type":"null"}],"title":"Assessment Info"},"reading_materials":{"anyOf":[{"type":"string"},{"type":"null"}],"title":"Reading Materials"},"category":{"anyOf":[{"type":"string"},{"type":"null"}],"title":"Category"},"academic_year":{"anyOf":[{"type":"string"},{"type":"null"}],"title":"Academic Year"},"semester":{"anyOf":[{"type":"string"},{"type":"null"}],"title":"Semester"},"schedule":{"anyOf":[{},{"type":"null"}],"title":"Schedule"},"start_date":{"anyOf":[{"type":"string","format":"date-time"},{"type":"null"}],"title":"Start Date"},"end_date":{"anyOf":[{"type":"string","format":"date-time"},{"type":"null"}],"title":"End Date"},"published":{"anyOf":[{"type":"boolean"},{"type":"null"}],"title":"Published"},"materials":{"anyOf":[{"items":{"type":"string"},"type":"array"},{"type":"null"}],"title":"Materials"},"order":{"anyOf":[{"type":"integer"},{"type":"null"}],"title":"Order"}},"type":"object","title":"CourseUpdate"},"CourseUsersLink":{"properties":{"user_ids":{"items":{"type":"string","format":"uuid"},"type":"array","title":"User Ids"}},"type":"object","required":["user_ids"],"title":"CourseUsersLink"},"EventType":{"type":"string","enum":["holiday","break_start","break_end","semester_start","semester_end","exam_period","registration"],"title":"EventType"},"ForumPost":{"properties":{"content":{"type":"string","title":"Content"},"id":{"type":"string","format":"uuid","title":"Id"},"thread_id":{"type":"string","format":"uuid","title":"Thread Id"},"author_id":{"type":"string","format":"uuid","title":"Author Id"},"created_at":{"type":"string","format":"date-time","title":"Created At"},"author":{"$ref":"#/components/schemas/User"}},"type":"object","required":["content","id","thread_id","author_id","created_at","author"],"title":"ForumPost"},"ForumPostCreate":{"properties":{"content":{"type":"string","title":"Content"}},"type":"object","required":["content"],"title":"ForumPostCreate"},"ForumThread":{"properties":{"title":{"type":"string","title":"Title"},"id":{"type":"string","format":"uuid","title":"Id"},"course_id":{"type":"string","format":"uuid","title":"Course Id"},"author_id":{"type":"string","format":"uuid","title":"Author Id"},"created_at":{"type":"string","format":"date-time","title":"Created At"},"author":{"$ref":"#/components/schemas/User"}},"type":"object","required":["title","id","course_id","author_id","created_at","author"],"title":"ForumThread"},"ForumThreadCreate":{"properties":{"title":{"type":"string","title":"Title"},"content":{"type":"string","title":"Content"}},"type":"object","required":["title","content"],"title":"ForumThreadCreate"},"ForumThreadWithPosts":{"properties":{"title":{"type":"string","title":"Title"},"id":{"type":"string","format":"uuid","title":"Id"},"course_id":{"type":"string","format":"uuid","title":"Course Id"},"author_id":{"type":"string","format":"uuid","title":"Author Id"},"created_at":{"type":"string","format":"date-time","title":"Created At"},"author":{"$ref":"#/components/schemas/User"},"posts":{"items":{"$ref":"#/components/schemas/ForumPost"},"type":"array","title":"Posts","default":[]}},"type":"object","required":["title","id","course_id","author_id","created_at","author"],"title":"ForumThreadWithPosts"},"HTTPValidationError":{"properties":{"detail":{"items":{"$ref":"#/components/schemas/ValidationError"},"type":"array","title":"Detail"}},"type":"object","title":"HTTPValidationError"},"Lecture":{"properties":{"title":{"type":"string","title":"Title"},"id":{"type":"string","format":"uuid","title":"Id"},"course_id":{"type":"string","format":"uuid","title":"Course Id"},"files":{"items":{"$ref":"#/components/schemas/LectureFile"},"type":"array","title":"Files","default":[]}},"type":"object","required":["title","id","course_id"],"title":"Lecture"},"LectureCreate":{"properties":{"title":{"type":"string","title":"Title"},"course_id":{"type":"string","format":"uuid","title":"Course Id"}},"type":"object","required":["title","course_id"],"title":"LectureCreate"},"LectureFile":{"properties":{"filename":{"type":"string","title":"Filename"},"folder_name":{"anyOf":[{"type":"string"},{"type":"null"}],"title":"Folder Name"},"is_folder":{"type":"boolean","title":"Is Folder","default":false},"id":{"type":"string","format":"uuid","title":"Id"},"stored_filename":{"type":"string","title":"Stored Filename"},"file_size":{"anyOf":[{"type":"string"},{"type":"null"}],"title":"File Size"},"file_type":{"anyOf":[{"type":"string"},{"type":"null"}],"title":"File Type"},"upload_date":{"type":"string","format":"date-time","title":"Upload Date"},"lecture_id":{"type":"string","format":"uuid","title":"Lecture Id"},"author":{"anyOf":[{"$ref":"#/components/schemas/User"},{"type":"null"}]}},"type":"object","required":["filename","id","stored_filename","upload_date","lecture_id"],"title":"LectureFile"},"LectureUpdate":{"properties":{"title":{"anyOf":[{"type":"string"},{"type":"null"}],"title":"Title"}},"type":"object","title":"LectureUpdate"},"News":{"properties":{"title":{"type":"string","title":"Title"},"content":{"type":"string","title":"Content"},"id":{"type":"string","format":"uuid","title":"Id"},"course_id":{"type":"string","format":"uuid","title":"Course Id"},"author":{"$ref":"#/components/schemas/User"},"created_at":{"type":"string","format":"date-time","title":"Created At"}},"type":"object","required":["title","content","id","course_id","author","created_at"],"title":"News"},"NewsCreate":{"properties":{"title":{"type":"string","title":"Title"},"content":{"type":"string","title":"Content"}},"type":"object","required":["title","content"],"title":"NewsCreate"},"NewsUpdate":{"properties":{"title":{"anyOf":[{"type":"string"},{"type":"null"}],"title":"Title"},"content":{"anyOf":[{"type":"string"},{"type":"null"}],"title":"Content"}},"type":"object","title":"NewsUpdate"},"ProgramType":{"type":"string","enum":["bachelor","master","phd","internship","online_course","certificate","diploma"],"title":"ProgramType"},"RefreshTokenRequest":{"properties":{"refresh_token":{"type":"string","title":"Refresh Token"}},"type":"object","required":["refresh_token"],"title":"RefreshTokenRequest"},"RoleType":{"type":"string","enum":["student","teacher","supervisor","admin"],"title":"RoleType"},"StudyProgram":{"properties":{"title":{"type":"string","title":"Title"},"description":{"anyOf":[{"type":"string"},{"type":"null"}],"title":"Description"},"academic_year":{"type":"string","title":"Academic Year"},"program_type":{"$ref":"#/components/schemas/ProgramType","default":"bachelor"},"start_date":{"type":"string","format":"date-time","title":"Start Date"},"end_date":{"anyOf":[{"type":"string","format":"date-time"},{"type":"null"}],"title":"End Date"},"published":{"type":"boolean","title":"Published","default":true},"id":{"type":"string","format":"uuid","title":"Id"},"supervisor":{"anyOf":[{"$ref":"#/components/schemas/User"},{"type":"null"}]},"students":{"items":{"$ref":"#/components/schemas/User"},"type":"array","title":"Students","default":[]},"teachers":{"items":{"$ref":"#/components/schemas/User"},"type":"array","title":"Teachers","default":[]}},"type":"object","required":["title","academic_year","start_date","id"],"title":"StudyProgram"},"StudyProgramCreate":{"properties":{"title":{"type":"string","title":"Title"},"description":{"anyOf":[{"type":"string"},{"type":"null"}],"title":"Description"},"academic_year":{"type":"string","title":"Academic Year"},"program_type":{"$ref":"#/components/schemas/ProgramType","default":"bachelor"},"start_date":{"type":"string","format":"date-time","title":"Start Date"},"end_date":{"anyOf":[{"type":"string","format":"date-time"},{"type":"null"}],"title":"End Date"},"published":{"type":"boolean","title":"Published","default":true}},"type":"object","required":["title","academic_year","start_date"],"title":"StudyProgramCreate"},"StudyProgramUpdate":{"properties":{"title":{"type":"string","title":"Title"},"description":{"anyOf":[{"type":"string"},{"type":"null"}],"title":"Description"},"academic_year":{"type":"string","title":"Academic Year"},"program_type":{"$ref":"#/components/schemas/ProgramType","default":"bachelor"},"start_date":{"type":"string","format":"date-time","title":"Start Date"},"end_date":{"anyOf":[{"type":"string","format":"date-time"},{"type":"null"}],"title":"End Date"},"published":{"type":"boolean","title":"Published","default":true}},"type":"object","required":["title","academic_year","start_date"],"title":"StudyProgramUpdate"},"StudyProgramUserLink":{"properties":{"user_id":{"type":"string","format":"uuid","title":"User Id"}},"type":"object","required":["user_id"],"title":"StudyProgramUserLink"},"StudyProgramUsersLink":{"properties":{"user_ids":{"items":{"type":"string","format":"uuid"},"type":"array","title":"User Ids"}},"type":"object","required":["user_ids"],"title":"StudyProgramUsersLink"},"Submission":{"properties":{"content":{"anyOf":[{"type":"string"},{"type":"null"}],"title":"Content"},"file_url":{"anyOf":[{"type":"string"},{"type":"null"}],"title":"File Url"},"id":{"type":"string","format":"uuid","title":"Id"},"assignment_id":{"type":"string","format":"uuid","title":"Assignment Id"},"student_id":{"type":"string","format":"uuid","title":"Student Id"},"submitted_at":{"type":"string","format":"date-time","title":"Submitted At"},"student":{"$ref":"#/components/schemas/User"}},"type":"object","required":["id","assignment_id","student_id","submitted_at","student"],"title":"Submission"},"SubmissionCreate":{"properties":{"content":{"anyOf":[{"type":"string"},{"type":"null"}],"title":"Content"},"file_url":{"anyOf":[{"type":"string"},{"type":"null"}],"title":"File Url"}},"type":"object","title":"SubmissionCreate"},"SupervisorAssignment":{"properties":{"supervisor_id":{"type":"string","format":"uuid","title":"Supervisor Id"}},"type":"object","required":["supervisor_id"],"title":"SupervisorAssignment"},"Token":{"properties":{"access_token":{"type":"string","title":"Access Token"},"refresh_token":{"type":"string","title":"Refresh Token"},"token_type":{"type":"string","title":"Token Type","default":"bearer"},"expires_in":{"type":"integer","title":"Expires In"}},"type":"object","required":["access_token","refresh_token","expires_in"],"title":"Token"},"User":{"properties":{"login":{"type":"string","title":"Login"},"email":{"type":"string","format":"email","title":"Email"},"phone_number":{"anyOf":[{"type":"string"},{"type":"null"}],"title":"Phone Number"},"role_type":{"$ref":"#/components/schemas/RoleType"},"name":{"anyOf":[{"type":"string"},{"type":"null"}],"title":"Name"},"surname":{"anyOf":[{"type":"string"},{"type":"null"}],"title":"Surname"},"id":{"type":"string","format":"uuid","title":"Id"},"is_active":{"type":"boolean","title":"Is Active"}},"type":"object","required":["login","email","role_type","id","is_active"],"title":"User"},"UserCreate":{"properties":{"login":{"type":"string","title":"Login"},"email":{"type":"string","format":"email","title":"Email"},"phone_number":{"anyOf":[{"type":"string"},{"type":"null"}],"title":"Phone Number"},"role_type":{"$ref":"#/components/schemas/RoleType"},"name":{"anyOf":[{"type":"string"},{"type":"null"}],"title":"Name"},"surname":{"anyOf":[{"type":"string"},{"type":"null"}],"title":"Surname"},"password":{"type":"string","title":"Password"},"academic_year":{"anyOf":[{"type":"integer"},{"type":"null"}],"title":"Academic Year"},"semester":{"anyOf":[{"type":"integer"},{"type":"null"}],"title":"Semester"},"auto_generate_login":{"anyOf":[{"type":"boolean"},{"type":"null"}],"title":"Auto Generate Login","default":false}},"type":"object","required":["login","email","role_type","password"],"title":"UserCreate"},"UserUpdate":{"properties":{"login":{"anyOf":[{"type":"string"},{"type":"null"}],"title":"Login"},"email":{"anyOf":[{"type":"string","format":"email"},{"type":"null"}],"title":"Email"},"phone_number":{"anyOf":[{"type":"string"},{"type":"null"}],"title":"Phone Number"},"password":{"anyOf":[{"type":"string"},{"type":"null"}],"title":"Password"},"name":{"anyOf":[{"type":"string"},{"type":"null"}],"title":"Name"},"surname":{"anyOf":[{"type":"string"},{"type":"null"}],"title":"Surname"},"role_type":{"anyOf":[{"$ref":"#/components/schemas/RoleType"},{"type":"null"}]},"is_active":{"anyOf":[{"type":"boolean"},{"type":"null"}],"title":"Is Active"}},"type":"object","title":"UserUpdate"},"ValidationError":{"properties":{"loc":{"items":{"anyOf":[{"type":"string"},{"type":"integer"}]},"type":"array","title":"Location"},"msg":{"type":"string","title":"Message"},"type":{"type":"string","title":"Error Type"}},"type":"object","required":["loc","msg","type"],"title":"ValidationError"}},"securitySchemes":{"OAuth2PasswordBearer":{"type":"oauth2","flows":{"password":{"scopes":{},"tokenUrl":"/api/v1/auth/login"}}}}}}